{
    "machine_info": {
        "node": "testing-docker-11121149-c59b-44ae-b0b6-97cb58bc6511", 
        "processor": "x86_64", 
        "machine": "x86_64", 
        "python_compiler": "", 
        "python_implementation": "PyPy", 
        "python_implementation_version": "5.4.0", 
        "python_version": "2.7.10", 
        "python_build": [
            "77392ad26350", 
            "Aug 28 2016"
        ], 
        "release": "4.4.0-47-generic", 
        "system": "Linux", 
        "cpu": {
            "vendor_id": "GenuineIntel", 
            "hardware": "", 
            "brand": "Intel(R) Xeon(R) CPU E5-2680 v2 @ 2.80GHz"
        }
    }, 
    "commit_info": {
        "id": "66ddb286f7649d4750a076571a698a47c7812a1b", 
        "dirty": false, 
        "project": "capnpy"
    }, 
    "benchmarks": [
        {
            "group": "getattr", 
            "name": "test_numeric[Instance-int64]", 
            "fullname": ".tox/pypy/site-packages/capnpy/benchmarks/test_benchmarks.py::TestGetAttr::()::test_numeric[Instance-int64]", 
            "params": {
                "schema": "Instance", 
                "numeric_type": "int64"
            }, 
            "param": "Instance-int64", 
            "extra_info": {
                "attribute_type": "int64"
            }, 
            "options": {
                "disable_gc": false, 
                "timer": "monotonic", 
                "min_rounds": 5, 
                "max_time": 1.0, 
                "min_time": 5e-06, 
                "warmup": 100000
            }, 
            "stats": {
                "min": 1.2965996575076133e-05, 
                "max": 0.0008369459974346682, 
                "mean": 1.3966891953198284e-05, 
                "stddev": 4.713887500095795e-06, 
                "rounds": 81103, 
                "median": 1.3388998922891915e-05, 
                "iqr": 5.099936970509589e-07, 
                "q1": 1.3229000614956021e-05, 
                "q3": 1.373899431200698e-05, 
                "iqr_outliers": 3933, 
                "stddev_outliers": 2911, 
                "outliers": "2911;3933", 
                "ld15iqr": 1.2965996575076133e-05, 
                "hd15iqr": 1.450399577151984e-05, 
                "iterations": 1
            }
        }, 
        {
            "group": "getattr", 
            "name": "test_numeric[Instance-int8]", 
            "fullname": ".tox/pypy/site-packages/capnpy/benchmarks/test_benchmarks.py::TestGetAttr::()::test_numeric[Instance-int8]", 
            "params": {
                "schema": "Instance", 
                "numeric_type": "int8"
            }, 
            "param": "Instance-int8", 
            "extra_info": {
                "attribute_type": "int8"
            }, 
            "options": {
                "disable_gc": false, 
                "timer": "monotonic", 
                "min_rounds": 5, 
                "max_time": 1.0, 
                "min_time": 5e-06, 
                "warmup": 100000
            }, 
            "stats": {
                "min": 1.2358003004919738e-05, 
                "max": 0.0009387829995830543, 
                "mean": 1.2977675274911434e-05, 
                "stddev": 4.5926941471471094e-06, 
                "rounds": 80077, 
                "median": 1.2737000361084938e-05, 
                "iqr": 3.8700090954080224e-07, 
                "q1": 1.2593998690135777e-05, 
                "q3": 1.298099959967658e-05, 
                "iqr_outliers": 1287, 
                "stddev_outliers": 739, 
                "outliers": "739;1287", 
                "ld15iqr": 1.2358003004919738e-05, 
                "hd15iqr": 1.3561999367084354e-05, 
                "iterations": 1
            }
        }, 
        {
            "group": "getattr", 
            "name": "test_numeric[Instance-int16]", 
            "fullname": ".tox/pypy/site-packages/capnpy/benchmarks/test_benchmarks.py::TestGetAttr::()::test_numeric[Instance-int16]", 
            "params": {
                "schema": "Instance", 
                "numeric_type": "int16"
            }, 
            "param": "Instance-int16", 
            "extra_info": {
                "attribute_type": "int16"
            }, 
            "options": {
                "disable_gc": false, 
                "timer": "monotonic", 
                "min_rounds": 5, 
                "max_time": 1.0, 
                "min_time": 5e-06, 
                "warmup": 100000
            }, 
            "stats": {
                "min": 1.3347998901735991e-05, 
                "max": 0.0007286899999598972, 
                "mean": 1.3915989236167041e-05, 
                "stddev": 3.695583181148531e-06, 
                "rounds": 77096, 
                "median": 1.3680000847671181e-05, 
                "iqr": 3.9099541027098894e-07, 
                "q1": 1.3545002730097622e-05, 
                "q3": 1.393599814036861e-05, 
                "iqr_outliers": 1529, 
                "stddev_outliers": 730, 
                "outliers": "730;1529", 
                "ld15iqr": 1.3347998901735991e-05, 
                "hd15iqr": 1.4523000572808087e-05, 
                "iterations": 1
            }
        }, 
        {
            "group": "getattr", 
            "name": "test_numeric[Instance-int32]", 
            "fullname": ".tox/pypy/site-packages/capnpy/benchmarks/test_benchmarks.py::TestGetAttr::()::test_numeric[Instance-int32]", 
            "params": {
                "schema": "Instance", 
                "numeric_type": "int32"
            }, 
            "param": "Instance-int32", 
            "extra_info": {
                "attribute_type": "int32"
            }, 
            "options": {
                "disable_gc": false, 
                "timer": "monotonic", 
                "min_rounds": 5, 
                "max_time": 1.0, 
                "min_time": 5e-06, 
                "warmup": 100000
            }, 
            "stats": {
                "min": 1.2716998753603548e-05, 
                "max": 0.0005882600016775541, 
                "mean": 1.3319238573220741e-05, 
                "stddev": 3.4769167591779074e-06, 
                "rounds": 80058, 
                "median": 1.3059994671493769e-05, 
                "iqr": 4.249959602020681e-07, 
                "q1": 1.2919001164846122e-05, 
                "q3": 1.334399712504819e-05, 
                "iqr_outliers": 1520, 
                "stddev_outliers": 804, 
                "outliers": "804;1520", 
                "ld15iqr": 1.2716998753603548e-05, 
                "hd15iqr": 1.3981996744405478e-05, 
                "iterations": 1
            }
        }, 
        {
            "group": "getattr", 
            "name": "test_numeric[Instance-uint8]", 
            "fullname": ".tox/pypy/site-packages/capnpy/benchmarks/test_benchmarks.py::TestGetAttr::()::test_numeric[Instance-uint8]", 
            "params": {
                "schema": "Instance", 
                "numeric_type": "uint8"
            }, 
            "param": "Instance-uint8", 
            "extra_info": {
                "attribute_type": "uint8"
            }, 
            "options": {
                "disable_gc": false, 
                "timer": "monotonic", 
                "min_rounds": 5, 
                "max_time": 1.0, 
                "min_time": 5e-06, 
                "warmup": 100000
            }, 
            "stats": {
                "min": 1.2670003343373537e-05, 
                "max": 0.0007271069989656098, 
                "mean": 1.3324714992471882e-05, 
                "stddev": 3.975187031384931e-06, 
                "rounds": 80691, 
                "median": 1.3066994142718613e-05, 
                "iqr": 4.1400198824703693e-07, 
                "q1": 1.2914999388158321e-05, 
                "q3": 1.3329001376405358e-05, 
                "iqr_outliers": 1729, 
                "stddev_outliers": 753, 
                "outliers": "753;1729", 
                "ld15iqr": 1.2670003343373537e-05, 
                "hd15iqr": 1.3950993889011443e-05, 
                "iterations": 1
            }
        }, 
        {
            "group": "getattr", 
            "name": "test_numeric[Instance-uint16]", 
            "fullname": ".tox/pypy/site-packages/capnpy/benchmarks/test_benchmarks.py::TestGetAttr::()::test_numeric[Instance-uint16]", 
            "params": {
                "schema": "Instance", 
                "numeric_type": "uint16"
            }, 
            "param": "Instance-uint16", 
            "extra_info": {
                "attribute_type": "uint16"
            }, 
            "options": {
                "disable_gc": false, 
                "timer": "monotonic", 
                "min_rounds": 5, 
                "max_time": 1.0, 
                "min_time": 5e-06, 
                "warmup": 100000
            }, 
            "stats": {
                "min": 1.2627999240066856e-05, 
                "max": 0.0010663509965525009, 
                "mean": 1.358782918362015e-05, 
                "stddev": 5.884725660019832e-06, 
                "rounds": 80730, 
                "median": 1.3081000361125916e-05, 
                "iqr": 4.4300395529717207e-07, 
                "q1": 1.29429972730577e-05, 
                "q3": 1.3386001228354871e-05, 
                "iqr_outliers": 3784, 
                "stddev_outliers": 2302, 
                "outliers": "2302;3784", 
                "ld15iqr": 1.2627999240066856e-05, 
                "hd15iqr": 1.405099465046078e-05, 
                "iterations": 1
            }
        }, 
        {
            "group": "getattr", 
            "name": "test_numeric[Instance-uint32]", 
            "fullname": ".tox/pypy/site-packages/capnpy/benchmarks/test_benchmarks.py::TestGetAttr::()::test_numeric[Instance-uint32]", 
            "params": {
                "schema": "Instance", 
                "numeric_type": "uint32"
            }, 
            "param": "Instance-uint32", 
            "extra_info": {
                "attribute_type": "uint32"
            }, 
            "options": {
                "disable_gc": false, 
                "timer": "monotonic", 
                "min_rounds": 5, 
                "max_time": 1.0, 
                "min_time": 5e-06, 
                "warmup": 100000
            }, 
            "stats": {
                "min": 1.239500124938786e-05, 
                "max": 0.0007369779996224679, 
                "mean": 1.2978799910517681e-05, 
                "stddev": 3.735051513829513e-06, 
                "rounds": 80458, 
                "median": 1.273599627893418e-05, 
                "iqr": 4.2000465327873826e-07, 
                "q1": 1.2591997801791877e-05, 
                "q3": 1.3012002455070615e-05, 
                "iqr_outliers": 1384, 
                "stddev_outliers": 762, 
                "outliers": "762;1384", 
                "ld15iqr": 1.239500124938786e-05, 
                "hd15iqr": 1.3642995327245444e-05, 
                "iterations": 1
            }
        }, 
        {
            "group": "getattr", 
            "name": "test_numeric[Instance-uint64]", 
            "fullname": ".tox/pypy/site-packages/capnpy/benchmarks/test_benchmarks.py::TestGetAttr::()::test_numeric[Instance-uint64]", 
            "params": {
                "schema": "Instance", 
                "numeric_type": "uint64"
            }, 
            "param": "Instance-uint64", 
            "extra_info": {
                "attribute_type": "uint64"
            }, 
            "options": {
                "disable_gc": false, 
                "timer": "monotonic", 
                "min_rounds": 5, 
                "max_time": 1.0, 
                "min_time": 5e-06, 
                "warmup": 100000
            }, 
            "stats": {
                "min": 1.2817996321246028e-05, 
                "max": 0.0007317260024137795, 
                "mean": 1.3277228964613916e-05, 
                "stddev": 3.6424934351727056e-06, 
                "rounds": 80724, 
                "median": 1.3026998203713447e-05, 
                "iqr": 4.1100429370999336e-07, 
                "q1": 1.2901997251901776e-05, 
                "q3": 1.3313001545611769e-05, 
                "iqr_outliers": 1431, 
                "stddev_outliers": 747, 
                "outliers": "747;1431", 
                "ld15iqr": 1.2817996321246028e-05, 
                "hd15iqr": 1.392999547533691e-05, 
                "iterations": 1
            }
        }, 
        {
            "group": "getattr", 
            "name": "test_numeric[Instance-float32]", 
            "fullname": ".tox/pypy/site-packages/capnpy/benchmarks/test_benchmarks.py::TestGetAttr::()::test_numeric[Instance-float32]", 
            "params": {
                "schema": "Instance", 
                "numeric_type": "float32"
            }, 
            "param": "Instance-float32", 
            "extra_info": {
                "attribute_type": "float32"
            }, 
            "options": {
                "disable_gc": false, 
                "timer": "monotonic", 
                "min_rounds": 5, 
                "max_time": 1.0, 
                "min_time": 5e-06, 
                "warmup": 100000
            }, 
            "stats": {
                "min": 1.2757998774759471e-05, 
                "max": 0.0007254919983097352, 
                "mean": 1.3314233897798524e-05, 
                "stddev": 3.6463178525477903e-06, 
                "rounds": 80880, 
                "median": 1.3081000361125916e-05, 
                "iqr": 4.219982656650245e-07, 
                "q1": 1.292899833060801e-05, 
                "q3": 1.3350996596273035e-05, 
                "iqr_outliers": 1423, 
                "stddev_outliers": 768, 
                "outliers": "768;1423", 
                "ld15iqr": 1.2757998774759471e-05, 
                "hd15iqr": 1.3983997632749379e-05, 
                "iterations": 1
            }
        }, 
        {
            "group": "getattr", 
            "name": "test_numeric[Instance-float64]", 
            "fullname": ".tox/pypy/site-packages/capnpy/benchmarks/test_benchmarks.py::TestGetAttr::()::test_numeric[Instance-float64]", 
            "params": {
                "schema": "Instance", 
                "numeric_type": "float64"
            }, 
            "param": "Instance-float64", 
            "extra_info": {
                "attribute_type": "float64"
            }, 
            "options": {
                "disable_gc": false, 
                "timer": "monotonic", 
                "min_rounds": 5, 
                "max_time": 1.0, 
                "min_time": 5e-06, 
                "warmup": 100000
            }, 
            "stats": {
                "min": 1.258600241271779e-05, 
                "max": 0.0007232539937831461, 
                "mean": 1.3292859038646617e-05, 
                "stddev": 3.635060452904252e-06, 
                "rounds": 80613, 
                "median": 1.304999750573188e-05, 
                "iqr": 3.579989424906671e-07, 
                "q1": 1.292699744226411e-05, 
                "q3": 1.3284996384754777e-05, 
                "iqr_outliers": 2313, 
                "stddev_outliers": 757, 
                "outliers": "757;2313", 
                "ld15iqr": 1.258600241271779e-05, 
                "hd15iqr": 1.3821998436469585e-05, 
                "iterations": 1
            }
        }, 
        {
            "group": "getattr", 
            "name": "test_numeric[Instance-group.field]", 
            "fullname": ".tox/pypy/site-packages/capnpy/benchmarks/test_benchmarks.py::TestGetAttr::()::test_numeric[Instance-group.field]", 
            "params": {
                "schema": "Instance", 
                "numeric_type": "group.field"
            }, 
            "param": "Instance-group.field", 
            "extra_info": {
                "attribute_type": "group.field"
            }, 
            "options": {
                "disable_gc": false, 
                "timer": "monotonic", 
                "min_rounds": 5, 
                "max_time": 1.0, 
                "min_time": 5e-06, 
                "warmup": 100000
            }, 
            "stats": {
                "min": 1.4946999726817012e-05, 
                "max": 0.0012519829979282804, 
                "mean": 1.5711294768771972e-05, 
                "stddev": 6.920678202541937e-06, 
                "rounds": 68720, 
                "median": 1.541600067866966e-05, 
                "iqr": 4.760004230774939e-07, 
                "q1": 1.5200996131170541e-05, 
                "q3": 1.5676996554248035e-05, 
                "iqr_outliers": 1481, 
                "stddev_outliers": 833, 
                "outliers": "833;1481", 
                "ld15iqr": 1.4946999726817012e-05, 
                "hd15iqr": 1.6391000826843083e-05, 
                "iterations": 1
            }
        }, 
        {
            "group": "getattr", 
            "name": "test_numeric[NamedTuple-int64]", 
            "fullname": ".tox/pypy/site-packages/capnpy/benchmarks/test_benchmarks.py::TestGetAttr::()::test_numeric[NamedTuple-int64]", 
            "params": {
                "schema": "NamedTuple", 
                "numeric_type": "int64"
            }, 
            "param": "NamedTuple-int64", 
            "extra_info": {
                "attribute_type": "int64"
            }, 
            "options": {
                "disable_gc": false, 
                "timer": "monotonic", 
                "min_rounds": 5, 
                "max_time": 1.0, 
                "min_time": 5e-06, 
                "warmup": 100000
            }, 
            "stats": {
                "min": 1.4714998542331159e-05, 
                "max": 0.0008554179948987439, 
                "mean": 1.5354550394043153e-05, 
                "stddev": 4.8003720173899065e-06, 
                "rounds": 67582, 
                "median": 1.5026002074591815e-05, 
                "iqr": 4.1799648897722363e-07, 
                "q1": 1.487600093241781e-05, 
                "q3": 1.5293997421395034e-05, 
                "iqr_outliers": 1882, 
                "stddev_outliers": 813, 
                "outliers": "813;1882", 
                "ld15iqr": 1.4714998542331159e-05, 
                "hd15iqr": 1.5920995792839676e-05, 
                "iterations": 1
            }
        }, 
        {
            "group": "getattr", 
            "name": "test_numeric[NamedTuple-int8]", 
            "fullname": ".tox/pypy/site-packages/capnpy/benchmarks/test_benchmarks.py::TestGetAttr::()::test_numeric[NamedTuple-int8]", 
            "params": {
                "schema": "NamedTuple", 
                "numeric_type": "int8"
            }, 
            "param": "NamedTuple-int8", 
            "extra_info": {
                "attribute_type": "int8"
            }, 
            "options": {
                "disable_gc": false, 
                "timer": "monotonic", 
                "min_rounds": 5, 
                "max_time": 1.0, 
                "min_time": 5e-06, 
                "warmup": 100000
            }, 
            "stats": {
                "min": 1.5050005458761007e-05, 
                "max": 0.0008327079995069653, 
                "mean": 1.565393259183192e-05, 
                "stddev": 4.618530153830211e-06, 
                "rounds": 69735, 
                "median": 1.5356999938376248e-05, 
                "iqr": 3.3899414120242e-07, 
                "q1": 1.5238001651596278e-05, 
                "q3": 1.5576995792798698e-05, 
                "iqr_outliers": 2292, 
                "stddev_outliers": 785, 
                "outliers": "785;2292", 
                "ld15iqr": 1.5050005458761007e-05, 
                "hd15iqr": 1.6085999959614128e-05, 
                "iterations": 1
            }
        }, 
        {
            "group": "getattr", 
            "name": "test_numeric[NamedTuple-int16]", 
            "fullname": ".tox/pypy/site-packages/capnpy/benchmarks/test_benchmarks.py::TestGetAttr::()::test_numeric[NamedTuple-int16]", 
            "params": {
                "schema": "NamedTuple", 
                "numeric_type": "int16"
            }, 
            "param": "NamedTuple-int16", 
            "extra_info": {
                "attribute_type": "int16"
            }, 
            "options": {
                "disable_gc": false, 
                "timer": "monotonic", 
                "min_rounds": 5, 
                "max_time": 1.0, 
                "min_time": 5e-06, 
                "warmup": 100000
            }, 
            "stats": {
                "min": 1.4106000890024006e-05, 
                "max": 0.0008557039982406422, 
                "mean": 1.465481562018545e-05, 
                "stddev": 4.585447282282698e-06, 
                "rounds": 71221, 
                "median": 1.4374003512784839e-05, 
                "iqr": 3.449968062341213e-07, 
                "q1": 1.4254997950047255e-05, 
                "q3": 1.4599994756281376e-05, 
                "iqr_outliers": 2237, 
                "stddev_outliers": 731, 
                "outliers": "731;2237", 
                "ld15iqr": 1.4106000890024006e-05, 
                "hd15iqr": 1.511799928266555e-05, 
                "iterations": 1
            }
        }, 
        {
            "group": "getattr", 
            "name": "test_numeric[NamedTuple-int32]", 
            "fullname": ".tox/pypy/site-packages/capnpy/benchmarks/test_benchmarks.py::TestGetAttr::()::test_numeric[NamedTuple-int32]", 
            "params": {
                "schema": "NamedTuple", 
                "numeric_type": "int32"
            }, 
            "param": "NamedTuple-int32", 
            "extra_info": {
                "attribute_type": "int32"
            }, 
            "options": {
                "disable_gc": false, 
                "timer": "monotonic", 
                "min_rounds": 5, 
                "max_time": 1.0, 
                "min_time": 5e-06, 
                "warmup": 100000
            }, 
            "stats": {
                "min": 1.4132994692772627e-05, 
                "max": 0.0008663020053063519, 
                "mean": 1.503287389342014e-05, 
                "stddev": 4.544007828704385e-06, 
                "rounds": 69745, 
                "median": 1.4769000699743629e-05, 
                "iqr": 2.8800423024222255e-07, 
                "q1": 1.4666999049950391e-05, 
                "q3": 1.4955003280192614e-05, 
                "iqr_outliers": 3291, 
                "stddev_outliers": 720, 
                "outliers": "720;3291", 
                "ld15iqr": 1.4235003618523479e-05, 
                "hd15iqr": 1.538799551781267e-05, 
                "iterations": 1
            }
        }, 
        {
            "group": "getattr", 
            "name": "test_numeric[NamedTuple-uint8]", 
            "fullname": ".tox/pypy/site-packages/capnpy/benchmarks/test_benchmarks.py::TestGetAttr::()::test_numeric[NamedTuple-uint8]", 
            "params": {
                "schema": "NamedTuple", 
                "numeric_type": "uint8"
            }, 
            "param": "NamedTuple-uint8", 
            "extra_info": {
                "attribute_type": "uint8"
            }, 
            "options": {
                "disable_gc": false, 
                "timer": "monotonic", 
                "min_rounds": 5, 
                "max_time": 1.0, 
                "min_time": 5e-06, 
                "warmup": 100000
            }, 
            "stats": {
                "min": 1.470300048822537e-05, 
                "max": 0.0008858360015437938, 
                "mean": 1.552136884510891e-05, 
                "stddev": 5.1859120430021755e-06, 
                "rounds": 69243, 
                "median": 1.5110999811440706e-05, 
                "iqr": 3.980021574534476e-07, 
                "q1": 1.4949997421354055e-05, 
                "q3": 1.5347999578807503e-05, 
                "iqr_outliers": 2797, 
                "stddev_outliers": 1699, 
                "outliers": "1699;2797", 
                "ld15iqr": 1.470300048822537e-05, 
                "hd15iqr": 1.594500645296648e-05, 
                "iterations": 1
            }
        }, 
        {
            "group": "getattr", 
            "name": "test_numeric[NamedTuple-uint16]", 
            "fullname": ".tox/pypy/site-packages/capnpy/benchmarks/test_benchmarks.py::TestGetAttr::()::test_numeric[NamedTuple-uint16]", 
            "params": {
                "schema": "NamedTuple", 
                "numeric_type": "uint16"
            }, 
            "param": "NamedTuple-uint16", 
            "extra_info": {
                "attribute_type": "uint16"
            }, 
            "options": {
                "disable_gc": false, 
                "timer": "monotonic", 
                "min_rounds": 5, 
                "max_time": 1.0, 
                "min_time": 5e-06, 
                "warmup": 100000
            }, 
            "stats": {
                "min": 1.450199488317594e-05, 
                "max": 0.0014886799981468357, 
                "mean": 1.5128806720812683e-05, 
                "stddev": 6.891274744147892e-06, 
                "rounds": 69195, 
                "median": 1.4854005712550133e-05, 
                "iqr": 3.480017767287791e-07, 
                "q1": 1.4705998182762414e-05, 
                "q3": 1.5053999959491193e-05, 
                "iqr_outliers": 2187, 
                "stddev_outliers": 720, 
                "outliers": "720;2187", 
                "ld15iqr": 1.450199488317594e-05, 
                "hd15iqr": 1.5576995792798698e-05, 
                "iterations": 1
            }
        }, 
        {
            "group": "getattr", 
            "name": "test_numeric[NamedTuple-uint32]", 
            "fullname": ".tox/pypy/site-packages/capnpy/benchmarks/test_benchmarks.py::TestGetAttr::()::test_numeric[NamedTuple-uint32]", 
            "params": {
                "schema": "NamedTuple", 
                "numeric_type": "uint32"
            }, 
            "param": "NamedTuple-uint32", 
            "extra_info": {
                "attribute_type": "uint32"
            }, 
            "options": {
                "disable_gc": false, 
                "timer": "monotonic", 
                "min_rounds": 5, 
                "max_time": 1.0, 
                "min_time": 5e-06, 
                "warmup": 100000
            }, 
            "stats": {
                "min": 1.417399471392855e-05, 
                "max": 0.0008654049961478449, 
                "mean": 1.4720641128721125e-05, 
                "stddev": 4.656621468188637e-06, 
                "rounds": 71094, 
                "median": 1.4445999113377184e-05, 
                "iqr": 3.949971869587898e-07, 
                "q1": 1.430200063623488e-05, 
                "q3": 1.469699782319367e-05, 
                "iqr_outliers": 1516, 
                "stddev_outliers": 731, 
                "outliers": "731;1516", 
                "ld15iqr": 1.417399471392855e-05, 
                "hd15iqr": 1.5289995644707233e-05, 
                "iterations": 1
            }
        }, 
        {
            "group": "getattr", 
            "name": "test_numeric[NamedTuple-uint64]", 
            "fullname": ".tox/pypy/site-packages/capnpy/benchmarks/test_benchmarks.py::TestGetAttr::()::test_numeric[NamedTuple-uint64]", 
            "params": {
                "schema": "NamedTuple", 
                "numeric_type": "uint64"
            }, 
            "param": "NamedTuple-uint64", 
            "extra_info": {
                "attribute_type": "uint64"
            }, 
            "options": {
                "disable_gc": false, 
                "timer": "monotonic", 
                "min_rounds": 5, 
                "max_time": 1.0, 
                "min_time": 5e-06, 
                "warmup": 100000
            }, 
            "stats": {
                "min": 1.5065998013596982e-05, 
                "max": 0.0009351469998364337, 
                "mean": 1.605104441886298e-05, 
                "stddev": 5.638098885132903e-06, 
                "rounds": 69329, 
                "median": 1.534500188427046e-05, 
                "iqr": 3.2699608709663153e-07, 
                "q1": 1.5243000234477222e-05, 
                "q3": 1.5569996321573853e-05, 
                "iqr_outliers": 5191, 
                "stddev_outliers": 3443, 
                "outliers": "3443;5191", 
                "ld15iqr": 1.5065998013596982e-05, 
                "hd15iqr": 1.6060999769251794e-05, 
                "iterations": 1
            }
        }, 
        {
            "group": "getattr", 
            "name": "test_numeric[NamedTuple-float32]", 
            "fullname": ".tox/pypy/site-packages/capnpy/benchmarks/test_benchmarks.py::TestGetAttr::()::test_numeric[NamedTuple-float32]", 
            "params": {
                "schema": "NamedTuple", 
                "numeric_type": "float32"
            }, 
            "param": "NamedTuple-float32", 
            "extra_info": {
                "attribute_type": "float32"
            }, 
            "options": {
                "disable_gc": false, 
                "timer": "monotonic", 
                "min_rounds": 5, 
                "max_time": 1.0, 
                "min_time": 5e-06, 
                "warmup": 100000
            }, 
            "stats": {
                "min": 1.5686004189774394e-05, 
                "max": 0.0008487779996357858, 
                "mean": 1.6382120603944295e-05, 
                "stddev": 4.930153837212401e-06, 
                "rounds": 66459, 
                "median": 1.60329946083948e-05, 
                "iqr": 3.709938027895987e-07, 
                "q1": 1.588900340721011e-05, 
                "q3": 1.625999720999971e-05, 
                "iqr_outliers": 2243, 
                "stddev_outliers": 821, 
                "outliers": "821;2243", 
                "ld15iqr": 1.5686004189774394e-05, 
                "hd15iqr": 1.6816993593238294e-05, 
                "iterations": 1
            }
        }, 
        {
            "group": "getattr", 
            "name": "test_numeric[NamedTuple-float64]", 
            "fullname": ".tox/pypy/site-packages/capnpy/benchmarks/test_benchmarks.py::TestGetAttr::()::test_numeric[NamedTuple-float64]", 
            "params": {
                "schema": "NamedTuple", 
                "numeric_type": "float64"
            }, 
            "param": "NamedTuple-float64", 
            "extra_info": {
                "attribute_type": "float64"
            }, 
            "options": {
                "disable_gc": false, 
                "timer": "monotonic", 
                "min_rounds": 5, 
                "max_time": 1.0, 
                "min_time": 5e-06, 
                "warmup": 100000
            }, 
            "stats": {
                "min": 1.4849996659904718e-05, 
                "max": 0.001817500000470318, 
                "mean": 1.5441555455910854e-05, 
                "stddev": 8.474090750177428e-06, 
                "rounds": 70393, 
                "median": 1.508700370322913e-05, 
                "iqr": 4.1500607039779425e-07, 
                "q1": 1.4946999726817012e-05, 
                "q3": 1.5362005797214806e-05, 
                "iqr_outliers": 3371, 
                "stddev_outliers": 790, 
                "outliers": "790;3371", 
                "ld15iqr": 1.4849996659904718e-05, 
                "hd15iqr": 1.5984995116014034e-05, 
                "iterations": 1
            }
        }, 
        {
            "group": "getattr", 
            "name": "test_numeric[NamedTuple-group.field]", 
            "fullname": ".tox/pypy/site-packages/capnpy/benchmarks/test_benchmarks.py::TestGetAttr::()::test_numeric[NamedTuple-group.field]", 
            "params": {
                "schema": "NamedTuple", 
                "numeric_type": "group.field"
            }, 
            "param": "NamedTuple-group.field", 
            "extra_info": {
                "attribute_type": "group.field"
            }, 
            "options": {
                "disable_gc": false, 
                "timer": "monotonic", 
                "min_rounds": 5, 
                "max_time": 1.0, 
                "min_time": 5e-06, 
                "warmup": 100000
            }, 
            "stats": {
                "min": 1.7004000255838037e-05, 
                "max": 0.0012139590035076253, 
                "mean": 1.7911977151426324e-05, 
                "stddev": 6.728524957482203e-06, 
                "rounds": 59365, 
                "median": 1.7450998711865395e-05, 
                "iqr": 4.4199987314641476e-07, 
                "q1": 1.7282000044360757e-05, 
                "q3": 1.772399991750717e-05, 
                "iqr_outliers": 3170, 
                "stddev_outliers": 1102, 
                "outliers": "1102;3170", 
                "ld15iqr": 1.7004000255838037e-05, 
                "hd15iqr": 1.8387007003184408e-05, 
                "iterations": 1
            }
        }, 
        {
            "group": "getattr", 
            "name": "test_numeric[Capnpy-int64]", 
            "fullname": ".tox/pypy/site-packages/capnpy/benchmarks/test_benchmarks.py::TestGetAttr::()::test_numeric[Capnpy-int64]", 
            "params": {
                "schema": "Capnpy", 
                "numeric_type": "int64"
            }, 
            "param": "Capnpy-int64", 
            "extra_info": {
                "attribute_type": "int64"
            }, 
            "options": {
                "disable_gc": false, 
                "timer": "monotonic", 
                "min_rounds": 5, 
                "max_time": 1.0, 
                "min_time": 5e-06, 
                "warmup": 100000
            }, 
            "stats": {
                "min": 2.3715001589152962e-05, 
                "max": 0.0028168480057502165, 
                "mean": 2.4780985574313222e-05, 
                "stddev": 1.757159629933619e-05, 
                "rounds": 41961, 
                "median": 2.4239998310804367e-05, 
                "iqr": 4.1000748751685023e-07, 
                "q1": 2.4059998395387083e-05, 
                "q3": 2.4470005882903934e-05, 
                "iqr_outliers": 1763, 
                "stddev_outliers": 250, 
                "outliers": "250;1763", 
                "ld15iqr": 2.3715001589152962e-05, 
                "hd15iqr": 2.5086999812629074e-05, 
                "iterations": 1
            }
        }, 
        {
            "group": "getattr", 
            "name": "test_numeric[Capnpy-int8]", 
            "fullname": ".tox/pypy/site-packages/capnpy/benchmarks/test_benchmarks.py::TestGetAttr::()::test_numeric[Capnpy-int8]", 
            "params": {
                "schema": "Capnpy", 
                "numeric_type": "int8"
            }, 
            "param": "Capnpy-int8", 
            "extra_info": {
                "attribute_type": "int8"
            }, 
            "options": {
                "disable_gc": false, 
                "timer": "monotonic", 
                "min_rounds": 5, 
                "max_time": 1.0, 
                "min_time": 5e-06, 
                "warmup": 100000
            }, 
            "stats": {
                "min": 2.3079999664332718e-05, 
                "max": 0.001985788003366906, 
                "mean": 2.403980399785124e-05, 
                "stddev": 1.291808096578275e-05, 
                "rounds": 43358, 
                "median": 2.35659972531721e-05, 
                "iqr": 3.5599805414676666e-07, 
                "q1": 2.3410000721924007e-05, 
                "q3": 2.3765998776070774e-05, 
                "iqr_outliers": 1813, 
                "stddev_outliers": 479, 
                "outliers": "479;1813", 
                "ld15iqr": 2.3079999664332718e-05, 
                "hd15iqr": 2.4300003133248538e-05, 
                "iterations": 1
            }
        }, 
        {
            "group": "getattr", 
            "name": "test_numeric[Capnpy-int16]", 
            "fullname": ".tox/pypy/site-packages/capnpy/benchmarks/test_benchmarks.py::TestGetAttr::()::test_numeric[Capnpy-int16]", 
            "params": {
                "schema": "Capnpy", 
                "numeric_type": "int16"
            }, 
            "param": "Capnpy-int16", 
            "extra_info": {
                "attribute_type": "int16"
            }, 
            "options": {
                "disable_gc": false, 
                "timer": "monotonic", 
                "min_rounds": 5, 
                "max_time": 1.0, 
                "min_time": 5e-06, 
                "warmup": 100000
            }, 
            "stats": {
                "min": 2.4064000172074884e-05, 
                "max": 0.0020344710064819083, 
                "mean": 2.49574886545672e-05, 
                "stddev": 1.3252036351517741e-05, 
                "rounds": 41378, 
                "median": 2.45140035985969e-05, 
                "iqr": 4.0499435272067785e-07, 
                "q1": 2.4341999960597605e-05, 
                "q3": 2.4746994313318282e-05, 
                "iqr_outliers": 1527, 
                "stddev_outliers": 408, 
                "outliers": "408;1527", 
                "ld15iqr": 2.4064000172074884e-05, 
                "hd15iqr": 2.5354995159432292e-05, 
                "iterations": 1
            }
        }, 
        {
            "group": "getattr", 
            "name": "test_numeric[Capnpy-int32]", 
            "fullname": ".tox/pypy/site-packages/capnpy/benchmarks/test_benchmarks.py::TestGetAttr::()::test_numeric[Capnpy-int32]", 
            "params": {
                "schema": "Capnpy", 
                "numeric_type": "int32"
            }, 
            "param": "Capnpy-int32", 
            "extra_info": {
                "attribute_type": "int32"
            }, 
            "options": {
                "disable_gc": false, 
                "timer": "monotonic", 
                "min_rounds": 5, 
                "max_time": 1.0, 
                "min_time": 5e-06, 
                "warmup": 100000
            }, 
            "stats": {
                "min": 2.38799984799698e-05, 
                "max": 0.002650849004567135, 
                "mean": 2.4810358596066938e-05, 
                "stddev": 1.6130549185183996e-05, 
                "rounds": 41949, 
                "median": 2.4216999008785933e-05, 
                "iqr": 4.129979060962796e-07, 
                "q1": 2.405700070085004e-05, 
                "q3": 2.446999860694632e-05, 
                "iqr_outliers": 1957, 
                "stddev_outliers": 254, 
                "outliers": "254;1957", 
                "ld15iqr": 2.38799984799698e-05, 
                "hd15iqr": 2.5091001589316875e-05, 
                "iterations": 1
            }
        }, 
        {
            "group": "getattr", 
            "name": "test_numeric[Capnpy-uint8]", 
            "fullname": ".tox/pypy/site-packages/capnpy/benchmarks/test_benchmarks.py::TestGetAttr::()::test_numeric[Capnpy-uint8]", 
            "params": {
                "schema": "Capnpy", 
                "numeric_type": "uint8"
            }, 
            "param": "Capnpy-uint8", 
            "extra_info": {
                "attribute_type": "uint8"
            }, 
            "options": {
                "disable_gc": false, 
                "timer": "monotonic", 
                "min_rounds": 5, 
                "max_time": 1.0, 
                "min_time": 5e-06, 
                "warmup": 100000
            }, 
            "stats": {
                "min": 2.3569002223666757e-05, 
                "max": 0.0029833469961886294, 
                "mean": 2.4430378684075046e-05, 
                "stddev": 1.814642953047052e-05, 
                "rounds": 42496, 
                "median": 2.3854998289607465e-05, 
                "iqr": 4.159956006333232e-07, 
                "q1": 2.3697000870015472e-05, 
                "q3": 2.4112996470648795e-05, 
                "iqr_outliers": 1535, 
                "stddev_outliers": 246, 
                "outliers": "246;1535", 
                "ld15iqr": 2.3569002223666757e-05, 
                "hd15iqr": 2.473700442351401e-05, 
                "iterations": 1
            }
        }, 
        {
            "group": "getattr", 
            "name": "test_numeric[Capnpy-uint16]", 
            "fullname": ".tox/pypy/site-packages/capnpy/benchmarks/test_benchmarks.py::TestGetAttr::()::test_numeric[Capnpy-uint16]", 
            "params": {
                "schema": "Capnpy", 
                "numeric_type": "uint16"
            }, 
            "param": "Capnpy-uint16", 
            "extra_info": {
                "attribute_type": "uint16"
            }, 
            "options": {
                "disable_gc": false, 
                "timer": "monotonic", 
                "min_rounds": 5, 
                "max_time": 1.0, 
                "min_time": 5e-06, 
                "warmup": 100000
            }, 
            "stats": {
                "min": 2.390200097579509e-05, 
                "max": 0.0020541199992294423, 
                "mean": 2.467452711784008e-05, 
                "stddev": 1.3867381286383161e-05, 
                "rounds": 41915, 
                "median": 2.4194996512960643e-05, 
                "iqr": 3.890017978847027e-07, 
                "q1": 2.4032000510487705e-05, 
                "q3": 2.4421002308372408e-05, 
                "iqr_outliers": 1674, 
                "stddev_outliers": 251, 
                "outliers": "251;1674", 
                "ld15iqr": 2.390200097579509e-05, 
                "hd15iqr": 2.5004999770317227e-05, 
                "iterations": 1
            }
        }, 
        {
            "group": "getattr", 
            "name": "test_numeric[Capnpy-uint32]", 
            "fullname": ".tox/pypy/site-packages/capnpy/benchmarks/test_benchmarks.py::TestGetAttr::()::test_numeric[Capnpy-uint32]", 
            "params": {
                "schema": "Capnpy", 
                "numeric_type": "uint32"
            }, 
            "param": "Capnpy-uint32", 
            "extra_info": {
                "attribute_type": "uint32"
            }, 
            "options": {
                "disable_gc": false, 
                "timer": "monotonic", 
                "min_rounds": 5, 
                "max_time": 1.0, 
                "min_time": 5e-06, 
                "warmup": 100000
            }, 
            "stats": {
                "min": 2.4128996301442385e-05, 
                "max": 0.0023373349977191538, 
                "mean": 2.514888907526906e-05, 
                "stddev": 1.5553463488457177e-05, 
                "rounds": 41227, 
                "median": 2.4551001843065023e-05, 
                "iqr": 4.309986252337694e-07, 
                "q1": 2.4398999812547117e-05, 
                "q3": 2.4829998437780887e-05, 
                "iqr_outliers": 1855, 
                "stddev_outliers": 257, 
                "outliers": "257;1855", 
                "ld15iqr": 2.4128996301442385e-05, 
                "hd15iqr": 2.547699841670692e-05, 
                "iterations": 1
            }
        }, 
        {
            "group": "getattr", 
            "name": "test_numeric[Capnpy-uint64]", 
            "fullname": ".tox/pypy/site-packages/capnpy/benchmarks/test_benchmarks.py::TestGetAttr::()::test_numeric[Capnpy-uint64]", 
            "params": {
                "schema": "Capnpy", 
                "numeric_type": "uint64"
            }, 
            "param": "Capnpy-uint64", 
            "extra_info": {
                "attribute_type": "uint64"
            }, 
            "options": {
                "disable_gc": false, 
                "timer": "monotonic", 
                "min_rounds": 5, 
                "max_time": 1.0, 
                "min_time": 5e-06, 
                "warmup": 100000
            }, 
            "stats": {
                "min": 0.0001016429960145615, 
                "max": 0.002205047996540088, 
                "mean": 0.00010829220800545592, 
                "stddev": 3.0391464503583368e-05, 
                "rounds": 9914, 
                "median": 0.00010477800242369995, 
                "iqr": 3.3679971238598228e-06, 
                "q1": 0.00010364199988543987, 
                "q3": 0.0001070099970092997, 
                "iqr_outliers": 1114, 
                "stddev_outliers": 225, 
                "outliers": "225;1114", 
                "ld15iqr": 0.0001016429960145615, 
                "hd15iqr": 0.00011207599891349673, 
                "iterations": 1
            }
        }, 
        {
            "group": "getattr", 
            "name": "test_numeric[Capnpy-float32]", 
            "fullname": ".tox/pypy/site-packages/capnpy/benchmarks/test_benchmarks.py::TestGetAttr::()::test_numeric[Capnpy-float32]", 
            "params": {
                "schema": "Capnpy", 
                "numeric_type": "float32"
            }, 
            "param": "Capnpy-float32", 
            "extra_info": {
                "attribute_type": "float32"
            }, 
            "options": {
                "disable_gc": false, 
                "timer": "monotonic", 
                "min_rounds": 5, 
                "max_time": 1.0, 
                "min_time": 5e-06, 
                "warmup": 100000
            }, 
            "stats": {
                "min": 2.3872002202551812e-05, 
                "max": 0.002052217001619283, 
                "mean": 2.482391756527188e-05, 
                "stddev": 1.3574603738729065e-05, 
                "rounds": 41728, 
                "median": 2.4305998522322625e-05, 
                "iqr": 4.284956958144903e-07, 
                "q1": 2.4124004994519055e-05, 
                "q3": 2.4552500690333545e-05, 
                "iqr_outliers": 1743, 
                "stddev_outliers": 473, 
                "outliers": "473;1743", 
                "ld15iqr": 2.3872002202551812e-05, 
                "hd15iqr": 2.5196000933647156e-05, 
                "iterations": 1
            }
        }, 
        {
            "group": "getattr", 
            "name": "test_numeric[Capnpy-float64]", 
            "fullname": ".tox/pypy/site-packages/capnpy/benchmarks/test_benchmarks.py::TestGetAttr::()::test_numeric[Capnpy-float64]", 
            "params": {
                "schema": "Capnpy", 
                "numeric_type": "float64"
            }, 
            "param": "Capnpy-float64", 
            "extra_info": {
                "attribute_type": "float64"
            }, 
            "options": {
                "disable_gc": false, 
                "timer": "monotonic", 
                "min_rounds": 5, 
                "max_time": 1.0, 
                "min_time": 5e-06, 
                "warmup": 100000
            }, 
            "stats": {
                "min": 2.3872999008744955e-05, 
                "max": 0.0025622429966460913, 
                "mean": 2.491345847395979e-05, 
                "stddev": 1.804323822742889e-05, 
                "rounds": 41833, 
                "median": 2.42609967244789e-05, 
                "iqr": 4.4599437387660146e-07, 
                "q1": 2.411500463495031e-05, 
                "q3": 2.456099900882691e-05, 
                "iqr_outliers": 1902, 
                "stddev_outliers": 252, 
                "outliers": "252;1902", 
                "ld15iqr": 2.3872999008744955e-05, 
                "hd15iqr": 2.522999420762062e-05, 
                "iterations": 1
            }
        }, 
        {
            "group": "getattr", 
            "name": "test_numeric[Capnpy-group.field]", 
            "fullname": ".tox/pypy/site-packages/capnpy/benchmarks/test_benchmarks.py::TestGetAttr::()::test_numeric[Capnpy-group.field]", 
            "params": {
                "schema": "Capnpy", 
                "numeric_type": "group.field"
            }, 
            "param": "Capnpy-group.field", 
            "extra_info": {
                "attribute_type": "group.field"
            }, 
            "options": {
                "disable_gc": false, 
                "timer": "monotonic", 
                "min_rounds": 5, 
                "max_time": 1.0, 
                "min_time": 5e-06, 
                "warmup": 100000
            }, 
            "stats": {
                "min": 2.982800651807338e-05, 
                "max": 0.00789541999984067, 
                "mean": 5.753839372804773e-05, 
                "stddev": 7.604363898160384e-05, 
                "rounds": 33932, 
                "median": 5.558999691857025e-05, 
                "iqr": 5.131005309522152e-06, 
                "q1": 5.305499507812783e-05, 
                "q3": 5.818600038764998e-05, 
                "iqr_outliers": 1374, 
                "stddev_outliers": 37, 
                "outliers": "37;1374", 
                "ld15iqr": 4.5378998038358986e-05, 
                "hd15iqr": 6.597599713131785e-05, 
                "iterations": 1
            }
        }, 
        {
            "group": "getattr", 
            "name": "test_text[Instance]", 
            "fullname": ".tox/pypy/site-packages/capnpy/benchmarks/test_benchmarks.py::TestGetAttr::()::test_text[Instance]", 
            "params": {
                "schema": "Instance"
            }, 
            "param": "Instance", 
            "extra_info": {
                "attribute_type": "text"
            }, 
            "options": {
                "disable_gc": false, 
                "timer": "monotonic", 
                "min_rounds": 5, 
                "max_time": 1.0, 
                "min_time": 5e-06, 
                "warmup": 100000
            }, 
            "stats": {
                "min": 3.735899372259155e-05, 
                "max": 0.0007412090053549036, 
                "mean": 3.923500412036091e-05, 
                "stddev": 7.228468560801221e-06, 
                "rounds": 22817, 
                "median": 3.850400389637798e-05, 
                "iqr": 4.960020305588841e-07, 
                "q1": 3.8263999158516526e-05, 
                "q3": 3.876000118907541e-05, 
                "iqr_outliers": 919, 
                "stddev_outliers": 394, 
                "outliers": "394;919", 
                "ld15iqr": 3.757699596462771e-05, 
                "hd15iqr": 3.950500104110688e-05, 
                "iterations": 1
            }
        }, 
        {
            "group": "getattr", 
            "name": "test_text[NamedTuple]", 
            "fullname": ".tox/pypy/site-packages/capnpy/benchmarks/test_benchmarks.py::TestGetAttr::()::test_text[NamedTuple]", 
            "params": {
                "schema": "NamedTuple"
            }, 
            "param": "NamedTuple", 
            "extra_info": {
                "attribute_type": "text"
            }, 
            "options": {
                "disable_gc": false, 
                "timer": "monotonic", 
                "min_rounds": 5, 
                "max_time": 1.0, 
                "min_time": 5e-06, 
                "warmup": 100000
            }, 
            "stats": {
                "min": 5.1939998229499906e-05, 
                "max": 0.0011517910024849698, 
                "mean": 5.485552480813929e-05, 
                "stddev": 1.5372199048253077e-05, 
                "rounds": 19396, 
                "median": 5.2493000112008303e-05, 
                "iqr": 3.78502591047436e-07, 
                "q1": 5.234599666437134e-05, 
                "q3": 5.272449925541878e-05, 
                "iqr_outliers": 3275, 
                "stddev_outliers": 669, 
                "outliers": "669;3275", 
                "ld15iqr": 5.1939998229499906e-05, 
                "hd15iqr": 5.3294999815989286e-05, 
                "iterations": 1
            }
        }, 
        {
            "group": "getattr", 
            "name": "test_text[Capnpy]", 
            "fullname": ".tox/pypy/site-packages/capnpy/benchmarks/test_benchmarks.py::TestGetAttr::()::test_text[Capnpy]", 
            "params": {
                "schema": "Capnpy"
            }, 
            "param": "Capnpy", 
            "extra_info": {
                "attribute_type": "text"
            }, 
            "options": {
                "disable_gc": false, 
                "timer": "monotonic", 
                "min_rounds": 5, 
                "max_time": 1.0, 
                "min_time": 5e-06, 
                "warmup": 100000
            }, 
            "stats": {
                "min": 5.993800004944205e-05, 
                "max": 0.004539604997262359, 
                "mean": 6.467431541355276e-05, 
                "stddev": 4.927455317941125e-05, 
                "rounds": 16686, 
                "median": 6.356549783959053e-05, 
                "iqr": 4.8620058805681765e-06, 
                "q1": 6.114199641160667e-05, 
                "q3": 6.600400229217485e-05, 
                "iqr_outliers": 310, 
                "stddev_outliers": 20, 
                "outliers": "20;310", 
                "ld15iqr": 5.993800004944205e-05, 
                "hd15iqr": 7.371900574071333e-05, 
                "iterations": 1
            }
        }, 
        {
            "group": "getattr", 
            "name": "test_struct[Instance]", 
            "fullname": ".tox/pypy/site-packages/capnpy/benchmarks/test_benchmarks.py::TestGetAttr::()::test_struct[Instance]", 
            "params": {
                "schema": "Instance"
            }, 
            "param": "Instance", 
            "extra_info": {
                "attribute_type": "struct"
            }, 
            "options": {
                "disable_gc": false, 
                "timer": "monotonic", 
                "min_rounds": 5, 
                "max_time": 1.0, 
                "min_time": 5e-06, 
                "warmup": 100000
            }, 
            "stats": {
                "min": 1.461600186303258e-05, 
                "max": 0.0008096960009424947, 
                "mean": 1.5419729887511517e-05, 
                "stddev": 5.1974748991578525e-06, 
                "rounds": 69955, 
                "median": 1.5034005627967417e-05, 
                "iqr": 4.2300234781578183e-07, 
                "q1": 1.4878998626954854e-05, 
                "q3": 1.5302000974770635e-05, 
                "iqr_outliers": 1684, 
                "stddev_outliers": 1041, 
                "outliers": "1041;1684", 
                "ld15iqr": 1.461600186303258e-05, 
                "hd15iqr": 1.5936995623633265e-05, 
                "iterations": 1
            }
        }, 
        {
            "group": "getattr", 
            "name": "test_struct[NamedTuple]", 
            "fullname": ".tox/pypy/site-packages/capnpy/benchmarks/test_benchmarks.py::TestGetAttr::()::test_struct[NamedTuple]", 
            "params": {
                "schema": "NamedTuple"
            }, 
            "param": "NamedTuple", 
            "extra_info": {
                "attribute_type": "struct"
            }, 
            "options": {
                "disable_gc": false, 
                "timer": "monotonic", 
                "min_rounds": 5, 
                "max_time": 1.0, 
                "min_time": 5e-06, 
                "warmup": 100000
            }, 
            "stats": {
                "min": 3.221099905204028e-05, 
                "max": 0.0010531190055189654, 
                "mean": 3.30758333939423e-05, 
                "stddev": 8.994080792125354e-06, 
                "rounds": 31249, 
                "median": 3.2379000913351774e-05, 
                "iqr": 2.6100315153598785e-07, 
                "q1": 3.227900015190244e-05, 
                "q3": 3.2540003303438425e-05, 
                "iqr_outliers": 2646, 
                "stddev_outliers": 633, 
                "outliers": "633;2646", 
                "ld15iqr": 3.221099905204028e-05, 
                "hd15iqr": 3.293200279586017e-05, 
                "iterations": 1
            }
        }, 
        {
            "group": "getattr", 
            "name": "test_struct[Capnpy]", 
            "fullname": ".tox/pypy/site-packages/capnpy/benchmarks/test_benchmarks.py::TestGetAttr::()::test_struct[Capnpy]", 
            "params": {
                "schema": "Capnpy"
            }, 
            "param": "Capnpy", 
            "extra_info": {
                "attribute_type": "struct"
            }, 
            "options": {
                "disable_gc": false, 
                "timer": "monotonic", 
                "min_rounds": 5, 
                "max_time": 1.0, 
                "min_time": 5e-06, 
                "warmup": 100000
            }, 
            "stats": {
                "min": 4.472799628274515e-05, 
                "max": 0.006259389003389515, 
                "mean": 4.602351852277393e-05, 
                "stddev": 5.7511178157034907e-05, 
                "rounds": 22502, 
                "median": 4.501000512391329e-05, 
                "iqr": 3.800014383159578e-07, 
                "q1": 4.486500256462023e-05, 
                "q3": 4.5245004002936184e-05, 
                "iqr_outliers": 1099, 
                "stddev_outliers": 9, 
                "outliers": "9;1099", 
                "ld15iqr": 4.472799628274515e-05, 
                "hd15iqr": 4.581599932862446e-05, 
                "iterations": 1
            }
        }, 
        {
            "group": "getattr", 
            "name": "test_list[Instance]", 
            "fullname": ".tox/pypy/site-packages/capnpy/benchmarks/test_benchmarks.py::TestGetAttr::()::test_list[Instance]", 
            "params": {
                "schema": "Instance"
            }, 
            "param": "Instance", 
            "extra_info": {
                "attribute_type": "list"
            }, 
            "options": {
                "disable_gc": false, 
                "timer": "monotonic", 
                "min_rounds": 5, 
                "max_time": 1.0, 
                "min_time": 5e-06, 
                "warmup": 100000
            }, 
            "stats": {
                "min": 1.4130993804428726e-05, 
                "max": 0.0008663279950269498, 
                "mean": 1.5031599723835431e-05, 
                "stddev": 5.060579304811488e-06, 
                "rounds": 73036, 
                "median": 1.4750999980606139e-05, 
                "iqr": 3.749955794773996e-07, 
                "q1": 1.4609002391807735e-05, 
                "q3": 1.4983997971285135e-05, 
                "iqr_outliers": 1984, 
                "stddev_outliers": 725, 
                "outliers": "725;1984", 
                "ld15iqr": 1.4130993804428726e-05, 
                "hd15iqr": 1.554699701955542e-05, 
                "iterations": 1
            }
        }, 
        {
            "group": "getattr", 
            "name": "test_list[NamedTuple]", 
            "fullname": ".tox/pypy/site-packages/capnpy/benchmarks/test_benchmarks.py::TestGetAttr::()::test_list[NamedTuple]", 
            "params": {
                "schema": "NamedTuple"
            }, 
            "param": "NamedTuple", 
            "extra_info": {
                "attribute_type": "list"
            }, 
            "options": {
                "disable_gc": false, 
                "timer": "monotonic", 
                "min_rounds": 5, 
                "max_time": 1.0, 
                "min_time": 5e-06, 
                "warmup": 100000
            }, 
            "stats": {
                "min": 3.144000220345333e-05, 
                "max": 0.0008011219979380257, 
                "mean": 3.228039743189222e-05, 
                "stddev": 7.18575127498599e-06, 
                "rounds": 31794, 
                "median": 3.171100252075121e-05, 
                "iqr": 2.0598963601514697e-07, 
                "q1": 3.164400550303981e-05, 
                "q3": 3.1849995139054954e-05, 
                "iqr_outliers": 2447, 
                "stddev_outliers": 580, 
                "outliers": "580;2447", 
                "ld15iqr": 3.144000220345333e-05, 
                "hd15iqr": 3.215899778297171e-05, 
                "iterations": 1
            }
        }, 
        {
            "group": "getattr", 
            "name": "test_list[Capnpy]", 
            "fullname": ".tox/pypy/site-packages/capnpy/benchmarks/test_benchmarks.py::TestGetAttr::()::test_list[Capnpy]", 
            "params": {
                "schema": "Capnpy"
            }, 
            "param": "Capnpy", 
            "extra_info": {
                "attribute_type": "list"
            }, 
            "options": {
                "disable_gc": false, 
                "timer": "monotonic", 
                "min_rounds": 5, 
                "max_time": 1.0, 
                "min_time": 5e-06, 
                "warmup": 100000
            }, 
            "stats": {
                "min": 4.6576999011449516e-05, 
                "max": 0.0065029959951061755, 
                "mean": 4.8544261921004045e-05, 
                "stddev": 6.205787546188841e-05, 
                "rounds": 21471, 
                "median": 4.711599467555061e-05, 
                "iqr": 4.260000423528254e-07, 
                "q1": 4.692200309364125e-05, 
                "q3": 4.734800313599408e-05, 
                "iqr_outliers": 1442, 
                "stddev_outliers": 23, 
                "outliers": "23;1442", 
                "ld15iqr": 4.6576999011449516e-05, 
                "hd15iqr": 4.7988003643695265e-05, 
                "iterations": 1
            }
        }, 
        {
            "group": "getattr_special", 
            "name": "test_which[Capnpy]", 
            "fullname": ".tox/pypy/site-packages/capnpy/benchmarks/test_benchmarks.py::TestGetAttrSpecial::()::test_which[Capnpy]", 
            "params": {
                "schema": "Capnpy"
            }, 
            "param": "Capnpy", 
            "extra_info": {}, 
            "options": {
                "disable_gc": false, 
                "timer": "monotonic", 
                "min_rounds": 5, 
                "max_time": 1.0, 
                "min_time": 5e-06, 
                "warmup": 100000
            }, 
            "stats": {
                "min": 2.4576002033427358e-05, 
                "max": 0.0025937969985534437, 
                "mean": 2.550068531304231e-05, 
                "stddev": 1.7128012218040205e-05, 
                "rounds": 41679, 
                "median": 2.5011002435348928e-05, 
                "iqr": 3.6400160752236843e-07, 
                "q1": 2.487500023562461e-05, 
                "q3": 2.523900184314698e-05, 
                "iqr_outliers": 1303, 
                "stddev_outliers": 236, 
                "outliers": "236;1303", 
                "ld15iqr": 2.4576002033427358e-05, 
                "hd15iqr": 2.5786001060623676e-05, 
                "iterations": 1
            }
        }, 
        {
            "group": "getattr_special", 
            "name": "test___which__[Capnpy]", 
            "fullname": ".tox/pypy/site-packages/capnpy/benchmarks/test_benchmarks.py::TestGetAttrSpecial::()::test___which__[Capnpy]", 
            "params": {
                "schema": "Capnpy"
            }, 
            "param": "Capnpy", 
            "extra_info": {}, 
            "options": {
                "disable_gc": false, 
                "timer": "monotonic", 
                "min_rounds": 5, 
                "max_time": 1.0, 
                "min_time": 5e-06, 
                "warmup": 100000
            }, 
            "stats": {
                "min": 2.422699617454782e-05, 
                "max": 0.0025592480014893226, 
                "mean": 2.5108835467539475e-05, 
                "stddev": 1.6274495367695885e-05, 
                "rounds": 42338, 
                "median": 2.4662003852427006e-05, 
                "iqr": 3.5499397199600935e-07, 
                "q1": 2.4543005565647036e-05, 
                "q3": 2.4897999537643045e-05, 
                "iqr_outliers": 1357, 
                "stddev_outliers": 210, 
                "outliers": "210;1357", 
                "ld15iqr": 2.422699617454782e-05, 
                "hd15iqr": 2.5430999812670052e-05, 
                "iterations": 1
            }
        }, 
        {
            "group": "getattr_special", 
            "name": "test_is_union[Capnpy]", 
            "fullname": ".tox/pypy/site-packages/capnpy/benchmarks/test_benchmarks.py::TestGetAttrSpecial::()::test_is_union[Capnpy]", 
            "params": {
                "schema": "Capnpy"
            }, 
            "param": "Capnpy", 
            "extra_info": {}, 
            "options": {
                "disable_gc": false, 
                "timer": "monotonic", 
                "min_rounds": 5, 
                "max_time": 1.0, 
                "min_time": 5e-06, 
                "warmup": 100000
            }, 
            "stats": {
                "min": 2.5129993446171284e-05, 
                "max": 0.002140275995770935, 
                "mean": 2.6750685472186262e-05, 
                "stddev": 1.424798465819418e-05, 
                "rounds": 39559, 
                "median": 2.628200309118256e-05, 
                "iqr": 3.71997884940356e-07, 
                "q1": 2.6144000003114343e-05, 
                "q3": 2.65159978880547e-05, 
                "iqr_outliers": 1299, 
                "stddev_outliers": 264, 
                "outliers": "264;1299", 
                "ld15iqr": 2.5588000426068902e-05, 
                "hd15iqr": 2.707399835344404e-05, 
                "iterations": 1
            }
        }, 
        {
            "group": "hash_int", 
            "name": "test_hash_ints[Instance]", 
            "fullname": ".tox/pypy/site-packages/capnpy/benchmarks/test_benchmarks.py::TestHash::()::test_hash_ints[Instance]", 
            "params": {
                "schema": "Instance"
            }, 
            "param": "Instance", 
            "extra_info": {
                "schema": "Instance", 
                "type": "int64"
            }, 
            "options": {
                "disable_gc": false, 
                "timer": "monotonic", 
                "min_rounds": 5, 
                "max_time": 1.0, 
                "min_time": 5e-06, 
                "warmup": 100000
            }, 
            "stats": {
                "min": 2.430400490993634e-05, 
                "max": 0.0013697470058104955, 
                "mean": 2.5665531808113005e-05, 
                "stddev": 1.0486586991481618e-05, 
                "rounds": 41794, 
                "median": 2.514799780328758e-05, 
                "iqr": 5.729962140321732e-07, 
                "q1": 2.493100328138098e-05, 
                "q3": 2.5503999495413154e-05, 
                "iqr_outliers": 3850, 
                "stddev_outliers": 286, 
                "outliers": "286;3850", 
                "ld15iqr": 2.430400490993634e-05, 
                "hd15iqr": 2.6368994440417737e-05, 
                "iterations": 1
            }
        }, 
        {
            "group": "hash_int", 
            "name": "test_hash_ints[NamedTuple]", 
            "fullname": ".tox/pypy/site-packages/capnpy/benchmarks/test_benchmarks.py::TestHash::()::test_hash_ints[NamedTuple]", 
            "params": {
                "schema": "NamedTuple"
            }, 
            "param": "NamedTuple", 
            "extra_info": {
                "schema": "NamedTuple", 
                "type": "int64"
            }, 
            "options": {
                "disable_gc": false, 
                "timer": "monotonic", 
                "min_rounds": 5, 
                "max_time": 1.0, 
                "min_time": 5e-06, 
                "warmup": 100000
            }, 
            "stats": {
                "min": 8.077200618572533e-05, 
                "max": 0.0008465339997201227, 
                "mean": 8.892269161730748e-05, 
                "stddev": 1.4038922375341967e-05, 
                "rounds": 12341, 
                "median": 8.605099719716236e-05, 
                "iqr": 4.673504008678719e-06, 
                "q1": 8.424775114690419e-05, 
                "q3": 8.892125515558291e-05, 
                "iqr_outliers": 1034, 
                "stddev_outliers": 794, 
                "outliers": "794;1034", 
                "ld15iqr": 8.077200618572533e-05, 
                "hd15iqr": 9.595399751560763e-05, 
                "iterations": 1
            }
        }, 
        {
            "group": "hash_int", 
            "name": "test_hash_ints[Capnpy]", 
            "fullname": ".tox/pypy/site-packages/capnpy/benchmarks/test_benchmarks.py::TestHash::()::test_hash_ints[Capnpy]", 
            "params": {
                "schema": "Capnpy"
            }, 
            "param": "Capnpy", 
            "extra_info": {
                "schema": "Capnpy", 
                "type": "int64"
            }, 
            "options": {
                "disable_gc": false, 
                "timer": "monotonic", 
                "min_rounds": 5, 
                "max_time": 1.0, 
                "min_time": 5e-06, 
                "warmup": 100000
            }, 
            "stats": {
                "min": 4.301399894757196e-05, 
                "max": 0.004550623998511583, 
                "mean": 4.4633226633122965e-05, 
                "stddev": 4.203295577947388e-05, 
                "rounds": 23345, 
                "median": 4.34849935118109e-05, 
                "iqr": 3.5999983083456755e-07, 
                "q1": 4.330700176069513e-05, 
                "q3": 4.36670015915297e-05, 
                "iqr_outliers": 1442, 
                "stddev_outliers": 104, 
                "outliers": "104;1442", 
                "ld15iqr": 4.301399894757196e-05, 
                "hd15iqr": 4.420900222612545e-05, 
                "iterations": 1
            }
        }, 
        {
            "group": "hash_int", 
            "name": "test_hash_ints_tuple", 
            "fullname": ".tox/pypy/site-packages/capnpy/benchmarks/test_benchmarks.py::TestHash::()::test_hash_ints_tuple", 
            "params": null, 
            "param": null, 
            "extra_info": {
                "schema": "tuple", 
                "type": "int64"
            }, 
            "options": {
                "disable_gc": false, 
                "timer": "monotonic", 
                "min_rounds": 5, 
                "max_time": 1.0, 
                "min_time": 5e-06, 
                "warmup": 100000
            }, 
            "stats": {
                "min": 8.789999992586672e-05, 
                "max": 0.0008871579993865453, 
                "mean": 0.00010376430137843288, 
                "stddev": 1.530993028285708e-05, 
                "rounds": 11950, 
                "median": 0.00010090200157719664, 
                "iqr": 8.682996849529445e-06, 
                "q1": 9.741199755808339e-05, 
                "q3": 0.00010609499440761283, 
                "iqr_outliers": 798, 
                "stddev_outliers": 803, 
                "outliers": "803;798", 
                "ld15iqr": 8.789999992586672e-05, 
                "hd15iqr": 0.00011916400399059057, 
                "iterations": 1
            }
        }, 
        {
            "group": "hash_str", 
            "name": "test_hash_str[Instance]", 
            "fullname": ".tox/pypy/site-packages/capnpy/benchmarks/test_benchmarks.py::TestHash::()::test_hash_str[Instance]", 
            "params": {
                "schema": "Instance"
            }, 
            "param": "Instance", 
            "extra_info": {
                "schema": "Instance", 
                "type": "str"
            }, 
            "options": {
                "disable_gc": false, 
                "timer": "monotonic", 
                "min_rounds": 5, 
                "max_time": 1.0, 
                "min_time": 5e-06, 
                "warmup": 100000
            }, 
            "stats": {
                "min": 4.563899710774422e-05, 
                "max": 0.0011292350027360953, 
                "mean": 4.667864751444252e-05, 
                "stddev": 1.053424883193065e-05, 
                "rounds": 22172, 
                "median": 4.60700030089356e-05, 
                "iqr": 5.059991963207722e-07, 
                "q1": 4.586300201481208e-05, 
                "q3": 4.6369001211132854e-05, 
                "iqr_outliers": 1033, 
                "stddev_outliers": 281, 
                "outliers": "281;1033", 
                "ld15iqr": 4.563899710774422e-05, 
                "hd15iqr": 4.71399980597198e-05, 
                "iterations": 1
            }
        }, 
        {
            "group": "hash_str", 
            "name": "test_hash_str[NamedTuple]", 
            "fullname": ".tox/pypy/site-packages/capnpy/benchmarks/test_benchmarks.py::TestHash::()::test_hash_str[NamedTuple]", 
            "params": {
                "schema": "NamedTuple"
            }, 
            "param": "NamedTuple", 
            "extra_info": {
                "schema": "NamedTuple", 
                "type": "str"
            }, 
            "options": {
                "disable_gc": false, 
                "timer": "monotonic", 
                "min_rounds": 5, 
                "max_time": 1.0, 
                "min_time": 5e-06, 
                "warmup": 100000
            }, 
            "stats": {
                "min": 9.365499863633886e-05, 
                "max": 0.0015936790005071089, 
                "mean": 0.00010095165615200474, 
                "stddev": 2.1902561375476603e-05, 
                "rounds": 10734, 
                "median": 9.766800212673843e-05, 
                "iqr": 4.385001375339925e-06, 
                "q1": 9.616700117476285e-05, 
                "q3": 0.00010055200255010277, 
                "iqr_outliers": 1088, 
                "stddev_outliers": 369, 
                "outliers": "369;1088", 
                "ld15iqr": 9.365499863633886e-05, 
                "hd15iqr": 0.0001071639999281615, 
                "iterations": 1
            }
        }, 
        {
            "group": "hash_str", 
            "name": "test_hash_str[Capnpy]", 
            "fullname": ".tox/pypy/site-packages/capnpy/benchmarks/test_benchmarks.py::TestHash::()::test_hash_str[Capnpy]", 
            "params": {
                "schema": "Capnpy"
            }, 
            "param": "Capnpy", 
            "extra_info": {
                "schema": "Capnpy", 
                "type": "str"
            }, 
            "options": {
                "disable_gc": false, 
                "timer": "monotonic", 
                "min_rounds": 5, 
                "max_time": 1.0, 
                "min_time": 5e-06, 
                "warmup": 100000
            }, 
            "stats": {
                "min": 0.0004899030027445406, 
                "max": 0.0015513550024479628, 
                "mean": 0.0005251109789134775, 
                "stddev": 5.1160515205731455e-05, 
                "rounds": 2035, 
                "median": 0.0005078990070614964, 
                "iqr": 4.038474799017422e-05, 
                "q1": 0.0004966045016772114, 
                "q3": 0.0005369892496673856, 
                "iqr_outliers": 140, 
                "stddev_outliers": 230, 
                "outliers": "230;140", 
                "ld15iqr": 0.0004899030027445406, 
                "hd15iqr": 0.0005978229964966886, 
                "iterations": 1
            }
        }, 
        {
            "group": "hash_str", 
            "name": "test_hash_str_tuple", 
            "fullname": ".tox/pypy/site-packages/capnpy/benchmarks/test_benchmarks.py::TestHash::()::test_hash_str_tuple", 
            "params": null, 
            "param": null, 
            "extra_info": {
                "schema": "tuple", 
                "type": "str"
            }, 
            "options": {
                "disable_gc": false, 
                "timer": "monotonic", 
                "min_rounds": 5, 
                "max_time": 1.0, 
                "min_time": 5e-06, 
                "warmup": 100000
            }, 
            "stats": {
                "min": 9.919599688146263e-05, 
                "max": 0.0009066529964911751, 
                "mean": 0.00010947102597012058, 
                "stddev": 1.4963978924441399e-05, 
                "rounds": 10125, 
                "median": 0.00010642599954735488, 
                "iqr": 8.21249523141887e-06, 
                "q1": 0.00010356125130783767, 
                "q3": 0.00011177374653925654, 
                "iqr_outliers": 434, 
                "stddev_outliers": 426, 
                "outliers": "426;434", 
                "ld15iqr": 9.919599688146263e-05, 
                "hd15iqr": 0.00012409500050125644, 
                "iterations": 1
            }
        }, 
        {
            "group": "buffered", 
            "name": "test_BufferedSocket", 
            "fullname": ".tox/pypy/site-packages/capnpy/benchmarks/test_buffered.py::TestBuffered::()::test_BufferedSocket", 
            "params": null, 
            "param": null, 
            "extra_info": {}, 
            "options": {
                "disable_gc": false, 
                "timer": "monotonic", 
                "min_rounds": 5, 
                "max_time": 1.0, 
                "min_time": 5e-06, 
                "warmup": 100000
            }, 
            "stats": {
                "min": 0.00738108000223292, 
                "max": 0.04387963000044692, 
                "mean": 0.00918636880636931, 
                "stddev": 0.0033136317041644434, 
                "rounds": 134, 
                "median": 0.008593009999458445, 
                "iqr": 0.0014134829980321229, 
                "q1": 0.008014913997612894, 
                "q3": 0.009428396995645016, 
                "iqr_outliers": 7, 
                "stddev_outliers": 7, 
                "outliers": "7;7", 
                "ld15iqr": 0.00738108000223292, 
                "hd15iqr": 0.012712634998024441, 
                "iterations": 1
            }
        }, 
        {
            "group": "buffered", 
            "name": "test_BufferedStream", 
            "fullname": ".tox/pypy/site-packages/capnpy/benchmarks/test_buffered.py::TestBuffered::()::test_BufferedStream", 
            "params": null, 
            "param": null, 
            "extra_info": {}, 
            "options": {
                "disable_gc": false, 
                "timer": "monotonic", 
                "min_rounds": 5, 
                "max_time": 1.0, 
                "min_time": 5e-06, 
                "warmup": 100000
            }, 
            "stats": {
                "min": 0.017052458999387454, 
                "max": 0.018746558998827823, 
                "mean": 0.0177272530707884, 
                "stddev": 0.000355026667282657, 
                "rounds": 57, 
                "median": 0.017692089997581206, 
                "iqr": 0.000382721003916231, 
                "q1": 0.01748666775165475, 
                "q3": 0.01786938875557098, 
                "iqr_outliers": 3, 
                "stddev_outliers": 14, 
                "outliers": "14;3", 
                "ld15iqr": 0.017052458999387454, 
                "hd15iqr": 0.01853062299778685, 
                "iterations": 1
            }
        }, 
        {
            "group": "buffered", 
            "name": "test_makefile", 
            "fullname": ".tox/pypy/site-packages/capnpy/benchmarks/test_buffered.py::TestBuffered::()::test_makefile", 
            "params": null, 
            "param": null, 
            "extra_info": {}, 
            "options": {
                "disable_gc": false, 
                "timer": "monotonic", 
                "min_rounds": 5, 
                "max_time": 1.0, 
                "min_time": 5e-06, 
                "warmup": 100000
            }, 
            "stats": {
                "min": 0.28548724300344475, 
                "max": 0.29027163900173036, 
                "mean": 0.2872740680031711, 
                "stddev": 0.002054569243873283, 
                "rounds": 5, 
                "median": 0.2861765900015598, 
                "iqr": 0.003179269999236567, 
                "q1": 0.28579330075444886, 
                "q3": 0.28897257075368543, 
                "iqr_outliers": 0, 
                "stddev_outliers": 1, 
                "outliers": "1;0", 
                "ld15iqr": 0.28548724300344475, 
                "hd15iqr": 0.29027163900173036, 
                "iterations": 1
            }
        }, 
        {
            "group": "ctor", 
            "name": "test_simple[Instance]", 
            "fullname": ".tox/pypy/site-packages/capnpy/benchmarks/test_ctor.py::TestCtor::()::test_simple[Instance]", 
            "params": {
                "schema": "Instance"
            }, 
            "param": "Instance", 
            "extra_info": {}, 
            "options": {
                "disable_gc": false, 
                "timer": "monotonic", 
                "min_rounds": 5, 
                "max_time": 1.0, 
                "min_time": 5e-06, 
                "warmup": 100000
            }, 
            "stats": {
                "min": 3.97800249629654e-06, 
                "max": 0.00046104549983283505, 
                "mean": 4.250134114915514e-06, 
                "stddev": 2.502672284656274e-06, 
                "rounds": 125377, 
                "median": 4.13049929193221e-06, 
                "iqr": 8.950155461207032e-08, 
                "q1": 4.091500159120187e-06, 
                "q3": 4.1810017137322575e-06, 
                "iqr_outliers": 12849, 
                "stddev_outliers": 796, 
                "outliers": "796;12849", 
                "ld15iqr": 3.97800249629654e-06, 
                "hd15iqr": 4.315497790230438e-06, 
                "iterations": 2
            }
        }, 
        {
            "group": "ctor", 
            "name": "test_simple[NamedTuple]", 
            "fullname": ".tox/pypy/site-packages/capnpy/benchmarks/test_ctor.py::TestCtor::()::test_simple[NamedTuple]", 
            "params": {
                "schema": "NamedTuple"
            }, 
            "param": "NamedTuple", 
            "extra_info": {}, 
            "options": {
                "disable_gc": false, 
                "timer": "monotonic", 
                "min_rounds": 5, 
                "max_time": 1.0, 
                "min_time": 5e-06, 
                "warmup": 100000
            }, 
            "stats": {
                "min": 2.8670001483988017e-06, 
                "max": 0.000529685497895116, 
                "mean": 4.266471845983618e-06, 
                "stddev": 2.1957704829528435e-06, 
                "rounds": 161447, 
                "median": 4.1480016079731286e-06, 
                "iqr": 1.3300086720846593e-07, 
                "q1": 4.100998921785504e-06, 
                "q3": 4.2339997889939696e-06, 
                "iqr_outliers": 12627, 
                "stddev_outliers": 1050, 
                "outliers": "1050;12627", 
                "ld15iqr": 3.903001925209537e-06, 
                "hd15iqr": 4.433502908796072e-06, 
                "iterations": 2
            }
        }, 
        {
            "group": "ctor", 
            "name": "test_simple[Capnpy]", 
            "fullname": ".tox/pypy/site-packages/capnpy/benchmarks/test_ctor.py::TestCtor::()::test_simple[Capnpy]", 
            "params": {
                "schema": "Capnpy"
            }, 
            "param": "Capnpy", 
            "extra_info": {}, 
            "options": {
                "disable_gc": false, 
                "timer": "monotonic", 
                "min_rounds": 5, 
                "max_time": 1.0, 
                "min_time": 5e-06, 
                "warmup": 100000
            }, 
            "stats": {
                "min": 2.4569999368395656e-05, 
                "max": 0.004772446998686064, 
                "mean": 3.644207204328129e-05, 
                "stddev": 3.293730470399709e-05, 
                "rounds": 43188, 
                "median": 3.507799920043908e-05, 
                "iqr": 5.480003892444074e-06, 
                "q1": 3.261999518144876e-05, 
                "q3": 3.809999907389283e-05, 
                "iqr_outliers": 1498, 
                "stddev_outliers": 484, 
                "outliers": "484;1498", 
                "ld15iqr": 2.4569999368395656e-05, 
                "hd15iqr": 4.6337001549545676e-05, 
                "iterations": 1
            }
        }, 
        {
            "group": "load", 
            "name": "test_load_from_file[Capnpy]", 
            "fullname": ".tox/pypy/site-packages/capnpy/benchmarks/test_message.py::TestMessage::()::test_load_from_file[Capnpy]", 
            "params": {
                "schema": "Capnpy"
            }, 
            "param": "Capnpy", 
            "extra_info": {}, 
            "options": {
                "disable_gc": false, 
                "timer": "monotonic", 
                "min_rounds": 5, 
                "max_time": 1.0, 
                "min_time": 5e-06, 
                "warmup": 100000
            }, 
            "stats": {
                "min": 0.19556202000239864, 
                "max": 0.20321070399950258, 
                "mean": 0.19805766619974746, 
                "stddev": 0.0032572115092858976, 
                "rounds": 5, 
                "median": 0.19659245300135808, 
                "iqr": 0.004677660994275357, 
                "q1": 0.19560394275140425, 
                "q3": 0.2002816037456796, 
                "iqr_outliers": 0, 
                "stddev_outliers": 1, 
                "outliers": "1;0", 
                "ld15iqr": 0.19556202000239864, 
                "hd15iqr": 0.20321070399950258, 
                "iterations": 1
            }
        }, 
        {
            "group": "load", 
            "name": "test_load_from_socket[Capnpy]", 
            "fullname": ".tox/pypy/site-packages/capnpy/benchmarks/test_message.py::TestMessage::()::test_load_from_socket[Capnpy]", 
            "params": {
                "schema": "Capnpy"
            }, 
            "param": "Capnpy", 
            "extra_info": {}, 
            "options": {
                "disable_gc": false, 
                "timer": "monotonic", 
                "min_rounds": 5, 
                "max_time": 1.0, 
                "min_time": 5e-06, 
                "warmup": 100000
            }, 
            "stats": {
                "min": 0.18957385199610144, 
                "max": 0.2146982830017805, 
                "mean": 0.20230735499977268, 
                "stddev": 0.009020442910176035, 
                "rounds": 7, 
                "median": 0.20047402100317413, 
                "iqr": 0.013488371745552286, 
                "q1": 0.19582148950212286, 
                "q3": 0.20930986124767514, 
                "iqr_outliers": 0, 
                "stddev_outliers": 2, 
                "outliers": "2;0", 
                "ld15iqr": 0.18957385199610144, 
                "hd15iqr": 0.2146982830017805, 
                "iterations": 1
            }
        }
    ], 
    "datetime": "2016-11-14T11:15:05.340712", 
    "version": "3.1.0a1"
}